geobbox/__init__.py
geobbox/geobbox.py
geobbox/py.typed
geobbox/split.py
geobbox/utm.py
geobbox-0.1.1.dist-info/licenses/LICENSE
geobbox-0.1.1.dist-info/WHEEL
geobbox-0.1.1.dist-info/METADATA
geobbox-0.1.1.dist-info/RECORD
