Metadata-Version: 2.4
Name: geobbox
Version: 0.1.1
Summary: A Python library to manipulate georeferenced bounding boxes.
Author-email: Gabriel Belouze <gabriel@belouze.com>
Requires-Python: >=3.10
Classifier: Development Status :: 2 - Pre-Alpha
Classifier: Intended Audience :: Developers
Classifier: License :: OSI Approved :: MIT License
Classifier: Operating System :: OS Independent
Classifier: Programming Language :: Python
Classifier: Programming Language :: Python :: 3
Classifier: Programming Language :: Python :: 3.10
Classifier: Programming Language :: Python :: 3.11
License-File: LICENSE
Requires-Dist: earthengine-api
Requires-Dist: numpy
Requires-Dist: rasterio
Requires-Dist: shapely>=2.0.6
Requires-Dist: utm
Requires-Dist: mypy ; extra == "dev"
Requires-Dist: pytest ; extra == "dev"
Requires-Dist: pre-commit ; extra == "dev"
Requires-Dist: ruff ; extra == "dev"
Requires-Dist: pydoclint[flake8] ; extra == "dev"
Requires-Dist: sphinx ; extra == "doc"
Requires-Dist: sphinx_rtd_theme ; extra == "doc"
Requires-Dist: sphinxcontrib-napoleon ; extra == "doc"
Project-URL: source, https://github.com/gbelouze/geobbox
Project-URL: tracker, https://github.com/gbelouze/geobbox/issues
Provides-Extra: dev
Provides-Extra: doc
